tree_sitter_hokku/__about__.py
tree_sitter_hokku/__init__.py
tree_sitter_hokku-0.0.1.dist-info/METADATA
tree_sitter_hokku-0.0.1.dist-info/WHEEL
tree_sitter_hokku-0.0.1.dist-info/licenses/LICENSE.txt
tree_sitter_hokku-0.0.1.dist-info/RECORD
