Metadata-Version: 2.4
Name: tree-sitter-hokku
Version: 0.0.1
Project-URL: Documentation, https://github.com/xoudini/hokku#readme
Project-URL: Issues, https://github.com/xoudini/hokku/issues
Project-URL: Source, https://github.com/xoudini/hokku
License-Expression: Apache-2.0
License-File: LICENSE.txt
Classifier: Development Status :: 4 - Beta
Classifier: Programming Language :: Python
Classifier: Programming Language :: Python :: 3.8
Classifier: Programming Language :: Python :: 3.9
Classifier: Programming Language :: Python :: 3.10
Classifier: Programming Language :: Python :: 3.11
Classifier: Programming Language :: Python :: 3.12
Classifier: Programming Language :: Python :: Implementation :: CPython
Classifier: Programming Language :: Python :: Implementation :: PyPy
Requires-Python: >=3.8
